envoy/distribution/verify/__init__.py
envoy/distribution/verify/checker.py
envoy/distribution/verify/cmd.py
envoy/distribution/verify/exceptions.py
envoy/distribution/verify/py.typed
envoy.distribution.verify-0.0.11.dist-info/METADATA
envoy.distribution.verify-0.0.11.dist-info/WHEEL
envoy.distribution.verify-0.0.11.dist-info/entry_points.txt
envoy.distribution.verify-0.0.11.dist-info/namespace_packages.txt
envoy.distribution.verify-0.0.11.dist-info/top_level.txt
envoy.distribution.verify-0.0.11.dist-info/RECORD
