Metadata-Version: 2.1
Name: envoy.distribution.verify
Version: 0.0.11
Summary: "Package distribution verification tool used in Envoy proxy's CI"
Home-page: https://github.com/envoyproxy/pytooling/tree/main/envoy.distribution.verify
Author: Ryan Northey
Author-email: ryan@synca.io
Maintainer: Ryan Northey
Maintainer-email: ryan@synca.io
License: Apache Software License 2.0
Platform: UNKNOWN
Requires-Dist: aio.run.checker (>=0.5.7)
Requires-Dist: aiodocker
Requires-Dist: envoy.base.utils (>=0.3.9)
Requires-Dist: envoy.distribution.distrotest (>=0.0.7)
